{"cameraMode":{"drawMode":0,"name":"Shaded","section":"Shading Mode"},"sceneLighting":false,"audioPlay":false,"sceneViewState":{"m_AlwaysRefresh":false,"showFog":false,"showSkybox":false,"showFlares":false,"showImageEffects":false,"showParticleSystems":false,"showVisualEffectGraphs":true,"m_FxEnabled":true},"in2DMode":false,"pivot":{"x":-2.6274280548095705,"y":-2.106710910797119,"z":-2.519944667816162},"rotation":{"x":0.13274574279785157,"y":0.7984225153923035,"z":-0.19082579016685487,"w":0.555418074131012},"size":4.583469390869141,"orthographic":false}